torch_cosine_annealing/__init__.py
torch_cosine_annealing/cosine_annealing_with_warm_restarts.py
torch_cosine_annealing-0.1.3.dist-info/LICENSE
torch_cosine_annealing-0.1.3.dist-info/METADATA
torch_cosine_annealing-0.1.3.dist-info/WHEEL
torch_cosine_annealing-0.1.3.dist-info/top_level.txt
torch_cosine_annealing-0.1.3.dist-info/RECORD
