Metadata-Version: 2.1
Name: torch-cosine-annealing
Version: 0.1.3
Summary: Cosine annealing learning rate scheduler for PyTorch based on SGDR
Author-email: Steve Immanuel <iam.steve.immanuel@gmail.com>
License: MIT License
Project-URL: Homepage, https://github.com/SteveImmanuel/torch-cosine-annealing
Keywords: cosine-annealing,sgdr,torch,scheduler
Classifier: License :: OSI Approved :: MIT License
Classifier: Programming Language :: Python :: 3
Classifier: Operating System :: OS Independent
Requires-Python: >=3.8
License-File: LICENSE
Requires-Dist: torch >=1.7.0
Provides-Extra: dev
Requires-Dist: pytest ; extra == 'dev'
Requires-Dist: matplotlib ; extra == 'dev'
Requires-Dist: bumpver ; extra == 'dev'
